saltine/__init__.py
saltine/saltine.py
saltine-0.0.2.data/scripts/hello-saltine
saltine-0.0.2.dist-info/LICENSE.txt
saltine-0.0.2.dist-info/METADATA
saltine-0.0.2.dist-info/WHEEL
saltine-0.0.2.dist-info/entry_points.txt
saltine-0.0.2.dist-info/top_level.txt
saltine-0.0.2.dist-info/RECORD
