Metadata-Version: 2.1
Name: saltine
Version: 0.0.2
Summary: saltine - Toolkit for Haloplex sequencing
Home-page: UNKNOWN
Author: 
Author-email: 
License: MIT
Platform: UNKNOWN
Provides-Extra: dev
Requires-Dist: pytest ; extra == 'dev'
Requires-Dist: tox ; extra == 'dev'
